pantyp/__init__.py
pantyp-0.0.1.dist-info/METADATA
pantyp-0.0.1.dist-info/WHEEL
pantyp-0.0.1.dist-info/licenses/LICENSE
pantyp-0.0.1.dist-info/RECORD
