Metadata-Version: 2.4
Name: pantyp
Version: 0.0.1
Project-URL: Documentation, https://daizutabi.github.io/pantyp/
Project-URL: Source, https://github.com/daizutabi/pantyp
Project-URL: Issues, https://github.com/daizutabi/pantyp/issues
Author-email: daizutabi <daizutabi@gmail.com>
License: MIT License
License-File: LICENSE
Classifier: Development Status :: 4 - Beta
Classifier: Intended Audience :: Education
Classifier: Intended Audience :: Science/Research
Classifier: License :: OSI Approved :: MIT License
Classifier: Operating System :: OS Independent
Classifier: Programming Language :: Python
Classifier: Programming Language :: Python :: 3.10
Classifier: Programming Language :: Python :: 3.11
Classifier: Programming Language :: Python :: 3.12
Classifier: Programming Language :: Python :: 3.13
Classifier: Topic :: Documentation
Classifier: Topic :: Scientific/Engineering
Classifier: Topic :: Software Development :: Documentation
Classifier: Topic :: Text Processing :: Markup
Requires-Python: >=3.10
